<?xml version="1.0" encoding="UTF-8"?>
<document>
    <scene id="TLS_bridge_75" name="TLS_bridge_75">

        <part id="0">
            <filter type="objloader">
                <param type="string" key="filepath" value="/Dataset/BridgeModels/bridge_75/approach_slabs.obj" />
                <param type="string" key="up" value="z" />
            </filter>
        </part>
        <part id="1">
            <filter type="objloader">
                <param type="string" key="filepath" value="/Dataset/BridgeModels/bridge_75/back_walls.obj" />
                <param type="string" key="up" value="z" />
            </filter>
        </part>
        <part id="2">
            <filter type="objloader">
                <param type="string" key="filepath" value="/Dataset/BridgeModels/bridge_75/deck.obj" />
                <param type="string" key="up" value="z" />
            </filter>
        </part>
        <part id="3">
            <filter type="objloader">
                <param type="string" key="filepath" value="/Dataset/BridgeModels/bridge_75/piers.obj" />
                <param type="string" key="up" value="z" />
            </filter>
        </part>
        <part id="4">
            <filter type="objloader">
                <param type="string" key="filepath" value="/Dataset/BridgeModels/bridge_75/railings.obj" />
                <param type="string" key="up" value="z" />
            </filter>
        </part>
        <part id="5">
            <filter type="objloader">
                <param type="string" key="filepath" value="/Dataset/BridgeModels/bridge_75/wing_walls.obj" />
                <param type="string" key="up" value="z" />
            </filter>
        </part>
		
    </scene>
</document>